{"key":"idp/adapter/AuthorizationCode/5ZYrDG9CNMWB78DvMRxL_FRvHLdUkKfptumeqtFk-rT","payload":{"payload":{"iat":1700821531,"exp":1700822131,"accountId":"http://localhost:3000/Alice-pod/profile/card#me","authTime":1700821531,"codeChallenge":"qEa_KVnot0bwjCGf1WgxmaxnepU3yB2jRWznh70A5Ng","codeChallengeMethod":"S256","grantId":"mt-wiAPLfQYibKK_w3XwTbLVOgOxism_H6vqNcURKHc","redirectUri":"http://localhost:3001/agents/new/callback","resource":"http://example.com/","scope":"openid offline_access webid ","sessionUid":"6uhsH-qJ3kC9WFf_0vZhz","kind":"AuthorizationCode","jti":"5ZYrDG9CNMWB78DvMRxL_FRvHLdUkKfptumeqtFk-rT","clientId":"Gfrfwajec0YrXDZgh3DMA","consumed":1700821531}}}